{
	"id": "4SolExOiniCutdk",
	"json": "{\"id\":\"4SolExOiniCutdk\",\"url\":\"http://shopping.interpark.com/product/productInfo.do?prdNo=8155701906\",\"uniqueKey\":\"http://shopping.interpark.com/product/productInfo.do?prdNo=8155701906\",\"method\":\"GET\",\"noRetry\":false,\"retryCount\":0,\"errorMessages\":[],\"headers\":{},\"userData\":{\"label\":\"handleDetail\"}}",
	"method": "GET",
	"orderNo": 1663759250743,
	"retryCount": 0,
	"uniqueKey": "http://shopping.interpark.com/product/productInfo.do?prdNo=8155701906",
	"url": "http://shopping.interpark.com/product/productInfo.do?prdNo=8155701906"
}